<?xml version="1.0" encoding="UTF-8" standalone="no"?>
<configuration version="1.0.8.7">
  <General>
    <HarmonyPath path="../../../../../../microchip/harmony/v1_08_01"/>
    <Processor name=""/>
    <ForceOptimization flag="true"/>
    <MergeStrategy flag="USER_ALL"/>
  </General>
  <Manifest>
    <Files>
      <File>
        <Name>ISR_Support.h</Name>
        <Path>Header Files/FreeRTOS/portable/MPLAB/PIC32MX</Path>
      </File>
      <File>
        <Name>drv_tmr_mapping.h</Name>
        <Path>Header Files/framework/driver/tmr</Path>
      </File>
      <File>
        <Name>semphr.h</Name>
        <Path>Header Files/FreeRTOS</Path>
      </File>
      <File>
        <Name>driver_common.h</Name>
        <Path>Header Files/framework/driver</Path>
      </File>
      <File>
        <Name>queue.h</Name>
        <Path>Header Files/FreeRTOS</Path>
      </File>
      <File>
        <Name>portmacro.h</Name>
        <Path>Header Files/FreeRTOS/portable/MPLAB/PIC32MX</Path>
      </File>
      <File>
        <Name>drv_usart_byte_model.c</Name>
        <Path>Source Files/framework/driver/usart/src/dynamic</Path>
      </File>
      <File>
        <Name>croutine.c</Name>
        <Path>Source Files/FreeRTOS</Path>
      </File>
      <File>
        <Name>port_asm.S</Name>
        <Path>Source Files/FreeRTOS/portable/MPLAB/PIC32MX</Path>
      </File>
      <File>
        <Name>list.h</Name>
        <Path>Header Files/FreeRTOS</Path>
      </File>
      <File>
        <Name>driver.h</Name>
        <Path>Header Files/framework/driver</Path>
      </File>
      <File>
        <Name>peripheral_common.h</Name>
        <Path>Header Files/framework/peripheral</Path>
      </File>
      <File>
        <Name>sys_int_pic32.c</Name>
        <Path>Source Files/framework/system/int/src</Path>
      </File>
      <File>
        <Name>sys_clk.h</Name>
        <Path>Header Files/framework/system/clk</Path>
      </File>
      <File>
        <Name>port.c</Name>
        <Path>Source Files/FreeRTOS/portable/MPLAB/PIC32MX</Path>
      </File>
      <File>
        <Name>sys_int_private.h</Name>
        <Path>Header Files/framework/system/int/src</Path>
      </File>
      <File>
        <Name>deprecated_definitions.h</Name>
        <Path>Header Files/FreeRTOS</Path>
      </File>
      <File>
        <Name>system.h</Name>
        <Path>Header Files/framework/system</Path>
      </File>
      <File>
        <Name>drv_usart.h</Name>
        <Path>Header Files/framework/driver/usart</Path>
      </File>
      <File>
        <Name>drv_oc.h</Name>
        <Path>Header Files/framework/driver/oc</Path>
      </File>
      <File>
        <Name>timers.h</Name>
        <Path>Header Files/FreeRTOS</Path>
      </File>
      <File>
        <Name>heap_1.c</Name>
        <Path>Source Files/FreeRTOS/portable/MemMang</Path>
      </File>
      <File>
        <Name>task.h</Name>
        <Path>Header Files/FreeRTOS</Path>
      </File>
      <File>
        <Name>sys_int.h</Name>
        <Path>Header Files/framework/system/int</Path>
      </File>
      <File>
        <Name>osal_freertos.h</Name>
        <Path>Header Files/framework/osal/src</Path>
      </File>
      <File>
        <Name>osal_impl_basic.h</Name>
        <Path>Header Files/framework/osal/src</Path>
      </File>
      <File>
        <Name>peripheral_common_32bit.h</Name>
        <Path>Header Files/framework/peripheral</Path>
      </File>
      <File>
        <Name>drv_tmr_variant_mapping.h</Name>
        <Path>Header Files/framework/driver/tmr/src</Path>
      </File>
      <File>
        <Name>list.c</Name>
        <Path>Source Files/FreeRTOS</Path>
      </File>
      <File>
        <Name>drv_tmr.h</Name>
        <Path>Header Files/framework/driver/tmr</Path>
      </File>
      <File>
        <Name>sys_devcon.c</Name>
        <Path>Source Files/framework/system/devcon/src</Path>
      </File>
      <File>
        <Name>osal.h</Name>
        <Path>Header Files/framework/osal</Path>
      </File>
      <File>
        <Name>StackMacros.h</Name>
        <Path>Header Files/FreeRTOS</Path>
      </File>
      <File>
        <Name>drv_usart_local.h</Name>
        <Path>Header Files/framework/driver/usart/src</Path>
      </File>
      <File>
        <Name>osal_freertos.c</Name>
        <Path>Source Files/framework/osal/src</Path>
      </File>
      <File>
        <Name>tasks.c</Name>
        <Path>Source Files/FreeRTOS</Path>
      </File>
      <File>
        <Name>sys_ports.h</Name>
        <Path>Header Files/framework/system/ports</Path>
      </File>
      <File>
        <Name>projdefs.h</Name>
        <Path>Header Files/FreeRTOS</Path>
      </File>
      <File>
        <Name>drv_ic.h</Name>
        <Path>Header Files/framework/driver/ic</Path>
      </File>
      <File>
        <Name>portable.h</Name>
        <Path>Header Files/FreeRTOS</Path>
      </File>
      <File>
        <Name>drv_usart.c</Name>
        <Path>Source Files/framework/driver/usart/src/dynamic</Path>
      </File>
      <File>
        <Name>croutine.h</Name>
        <Path>Header Files/FreeRTOS</Path>
      </File>
      <File>
        <Name>sys_common.h</Name>
        <Path>Header Files/framework/system/common</Path>
      </File>
      <File>
        <Name>sys_buffer.h</Name>
        <Path>Header Files/framework/system/common</Path>
      </File>
      <File>
        <Name>event_groups.h</Name>
        <Path>Header Files/FreeRTOS</Path>
      </File>
      <File>
        <Name>osal_impl_none.h</Name>
        <Path>Header Files/framework/osal/src</Path>
      </File>
      <File>
        <Name>sys_clk_mapping.h</Name>
        <Path>Header Files/framework/system/clk</Path>
      </File>
      <File>
        <Name>osal_definitions.h</Name>
        <Path>Header Files/framework/osal</Path>
      </File>
      <File>
        <Name>sys_int_mapping.h</Name>
        <Path>Header Files/framework/system/int</Path>
      </File>
      <File>
        <Name>FreeRTOS.h</Name>
        <Path>Header Files/FreeRTOS</Path>
      </File>
      <File>
        <Name>gfx_palette.h</Name>
        <Path>Header Files/framework/gfx</Path>
      </File>
      <File>
        <Name>sys_devcon.h</Name>
        <Path>Header Files/framework/system/devcon</Path>
      </File>
      <File>
        <Name>event_groups.c</Name>
        <Path>Source Files/FreeRTOS</Path>
      </File>
      <File>
        <Name>sys_debug.h</Name>
        <Path>Header Files/framework/system/debug</Path>
      </File>
      <File>
        <Name>drv_usart_variant_mapping.h</Name>
        <Path>Header Files/framework/driver/usart/src</Path>
      </File>
      <File>
        <Name>sys_module.h</Name>
        <Path>Header Files/framework/system/common</Path>
      </File>
      <File>
        <Name>sys_devcon_pic32mx.c</Name>
        <Path>Source Files/framework/system/devcon/src</Path>
      </File>
      <File>
        <Name>sys_devcon_local.h</Name>
        <Path>Header Files/framework/system/devcon/src</Path>
      </File>
      <File>
        <Name>timers.c</Name>
        <Path>Source Files/FreeRTOS</Path>
      </File>
      <File>
        <Name>mpu_wrappers.h</Name>
        <Path>Header Files/FreeRTOS</Path>
      </File>
      <File>
        <Name>peripheral.h</Name>
        <Path>Header Files/framework/peripheral</Path>
      </File>
      <File>
        <Name>sys_queue.h</Name>
        <Path>Header Files/framework/system/common</Path>
      </File>
      <File>
        <Name>queue.c</Name>
        <Path>Source Files/FreeRTOS</Path>
      </File>
    </Files>
    <Templates>
      <Template>
        <Name>sys_ports_static.c</Name>
        <Path>Source Files/app/system_config/default/framework/system/ports/src</Path>
        <Checksum>95DFDD1603FE4DED042B76A806DFF3A5</Checksum>
      </Template>
      <Template>
        <Name>system_interrupt_a.S</Name>
        <Path>Source Files/app/system_config/default</Path>
        <Checksum>42112F51A6F22DEF68CEAABD80D2E2DC</Checksum>
      </Template>
      <Template>
        <Name>drv_tmr_static.h</Name>
        <Path>Header Files/app/system_config/default/framework/driver/tmr</Path>
        <Checksum>5B1227C9C8A50A58EB2DAB66BF09B4E6</Checksum>
      </Template>
      <Template>
        <Name>UART_TX.h</Name>
        <Path>Header Files/app</Path>
      </Template>
      <Template>
        <Name>JSON_Parser.h</Name>
        <Path>Header Files/app</Path>
      </Template>
      <Template>
        <Name>drv_tmr_mapping.c</Name>
        <Path>Source Files/app/system_config/default/framework/driver/tmr/src</Path>
        <Checksum>0651845480D5D3E21D8BF17EE68DBEAC</Checksum>
      </Template>
      <Template>
        <Name>PIC_interface.h</Name>
        <Path>Header Files/app</Path>
      </Template>
      <Template>
        <Name>UART_TX.c</Name>
        <Path>Source Files/app</Path>
      </Template>
      <Template>
        <Name>grid_handler.c</Name>
        <Path>Source Files/app</Path>
      </Template>
      <Template>
        <Name>FreeRTOSConfig.h</Name>
        <Path>Header Files/app/system_config/default</Path>
        <Checksum>375623C67A3F2F79B9F13FCEB2F47341</Checksum>
      </Template>
      <Template>
        <Name>UART_RX.h</Name>
        <Path>Header Files/app</Path>
      </Template>
      <Template>
        <Name>transmit_handler.h</Name>
        <Path>Header Files/app</Path>
      </Template>
      <Template>
        <Name>sys_clk_static.h</Name>
        <Path>Header Files/app/system_config/default/framework/system/clk</Path>
        <Checksum>B4BD59D8D7C4DA95DC5E3B57755FD352</Checksum>
      </Template>
      <Template>
        <Name>system_interrupt.c</Name>
        <Path>Source Files/app/system_config/default</Path>
        <Checksum>B9838B5A93B33285C4A7BFCBC13345B5</Checksum>
        <ProjectFileChecksum>B0019E9D6A9C2EF6A0441969E7E64B7C</ProjectFileChecksum>
      </Template>
      <Template>
        <Name>PIC_interface.c</Name>
        <Path>Source Files/app</Path>
      </Template>
      <Template>
        <Name>drv_oc_mapping.c</Name>
        <Path>Source Files/app/system_config/default/framework/driver/oc/src</Path>
        <Checksum>37E47DA142875F6105BF31AC89D55255</Checksum>
      </Template>
      <Template>
        <Name>sys_clk_static.c</Name>
        <Path>Source Files/app/system_config/default/framework/system/clk/src</Path>
        <Checksum>E8C935BED4628875A8C3428DDD07355C</Checksum>
      </Template>
      <Template>
        <Name>drv_ic_mapping.c</Name>
        <Path>Source Files/app/system_config/default/framework/driver/ic/src</Path>
        <Checksum>2C8DAE22C6B29920577BB32CBE6C6ED8</Checksum>
      </Template>
      <Template>
        <Name>drv_oc_static.c</Name>
        <Path>Source Files/app/system_config/default/framework/driver/oc/src</Path>
        <Checksum>DCDB709A7C82E3AEDD0E3687008A861E</Checksum>
        <ProjectFileChecksum>8AEFA8F75346F4D28933F4FF2DEE46CA</ProjectFileChecksum>
      </Template>
      <Template>
        <Name>system_init.c</Name>
        <Path>Source Files/app/system_config/default</Path>
        <Checksum>145617769D901DBC01CFEACF5813D2E3</Checksum>
      </Template>
      <Template>
        <Name>drv_oc_static.h</Name>
        <Path>Header Files/app/system_config/default/framework/driver/oc</Path>
        <Checksum>4FF078ACA4859F0FD658B7C07EE88CDD</Checksum>
      </Template>
      <Template>
        <Name>main.c</Name>
        <Path>Source Files/app</Path>
      </Template>
      <Template>
        <Name>drv_ic_static.c</Name>
        <Path>Source Files/app/system_config/default/framework/driver/ic/src</Path>
        <Checksum>8C7459AF1280E6D1E841B3A4DB8D9D37</Checksum>
      </Template>
      <Template>
        <Name>grid_handler.h</Name>
        <Path>Header Files/app</Path>
      </Template>
      <Template>
        <Name>JSON_Parser.c</Name>
        <Path>Source Files/app</Path>
      </Template>
      <Template>
        <Name>PING_Sensors.c</Name>
        <Path>Source Files/app</Path>
      </Template>
      <Template>
        <Name>system_definitions.h</Name>
        <Path>Header Files/app/system_config/default</Path>
        <Checksum>1AC690B4180323788B611E86F6C2A84E</Checksum>
      </Template>
      <Template>
        <Name>system_exceptions.c</Name>
        <Path>Source Files/app/system_config/default</Path>
        <Checksum>C111969CA43D6CEA1E9E33A6164E7AE0</Checksum>
      </Template>
      <Template>
        <Name>UART_RX.c</Name>
        <Path>Source Files/app</Path>
      </Template>
      <Template>
        <Name>system_tasks.c</Name>
        <Path>Source Files/app/system_config/default</Path>
        <Checksum>8DEDF24C660AC59C0204886B737EF096</Checksum>
      </Template>
      <Template>
        <Name>transmit_handler.c</Name>
        <Path>Source Files/app</Path>
      </Template>
      <Template>
        <Name>system_config.h</Name>
        <Path>Header Files/app/system_config/default</Path>
        <Checksum>FBE4E662D8923DD4EDD3D7F9D477666C</Checksum>
      </Template>
      <Template>
        <Name>drv_ic_static.h</Name>
        <Path>Header Files/app/system_config/default/framework/driver/ic</Path>
        <Checksum>B0DB9B924D9B4BAABE14A9540C6E6D97</Checksum>
      </Template>
      <Template>
        <Name>drv_tmr_static.c</Name>
        <Path>Source Files/app/system_config/default/framework/driver/tmr/src</Path>
        <Checksum>439B2651B49C9B83B11F40916BAD0BAD</Checksum>
      </Template>
      <Template>
        <Name>rtos_hooks.c</Name>
        <Path>Source Files/app/system_config/default</Path>
        <Checksum>FA52743264536E5207D2ADBE57B48D05</Checksum>
      </Template>
      <Template>
        <Name>PING_Sensors.h</Name>
        <Path>Header Files/app</Path>
      </Template>
    </Templates>
    <CompilerItems>
      <C32-AS>
        <Include value="../../../../../../../../microchip/harmony/v1_08_01/third_party/rtos/FreeRTOS/Source/portable/MPLAB/PIC32MX"/>
        <Include value="../../../../../../../../microchip/harmony/v1_08_01/third_party/rtos/FreeRTOS/Source/include"/>
        <Include value="../src/system_config/default"/>
      </C32-AS>
      <C32>
        <Include value="C:\Users\Daniel\Documents\VT 2016-2017\Embedded\Milestone_4\firmware\src"/>
        <Include value="C:\Users\Daniel\Documents\VT 2016-2017\Embedded\Milestone_4\firmware\src\system_config\default"/>
        <Include value="C:\Users\Daniel\Documents\VT 2016-2017\Embedded\Milestone_4\firmware\src\default"/>
        <Include value="C:\microchip\harmony\v1_08_01\framework"/>
        <Include value="C:\Users\Daniel\Documents\VT 2016-2017\Embedded\Milestone_4\firmware\src\system_config\default\framework"/>
        <Include value="../../../../../../../../microchip/harmony/v1_08_01/third_party/rtos/FreeRTOS/Source/portable/MPLAB/PIC32MX"/>
        <Include value="../../../../../../../../microchip/harmony/v1_08_01/third_party/rtos/FreeRTOS/Source/include"/>
        <Include value="../src/system_config/default"/>
        <Define value="__XC"/>
      </C32>
    </CompilerItems>
    <Libraries>
      <Library value="../../../../../../../../microchip/harmony/v1_08_01/framework/tcpip/src/crypto/aes_pic32mx.a"/>
      <Library value="../../../../../../../../microchip/harmony/v1_08_01/bin/framework/peripheral/PIC32MX795F512L_peripherals.a"/>
    </Libraries>
  </Manifest>
</configuration>
